puncover_riscv/__init__.py
puncover_riscv/backtrace_helper.py
puncover_riscv/builders.py
puncover_riscv/collector.py
puncover_riscv/gcc_tools.py
puncover_riscv/middleware.py
puncover_riscv/puncover_riscv.py
puncover_riscv/renderers.py
puncover_riscv/version.py
puncover_riscv/static/css/bootstrap.min.css
puncover_riscv/static/css/style.css
puncover_riscv/static/fonts/glyphicons-halflings-regular.eot
puncover_riscv/static/fonts/glyphicons-halflings-regular.svg
puncover_riscv/static/fonts/glyphicons-halflings-regular.ttf
puncover_riscv/static/fonts/glyphicons-halflings-regular.woff
puncover_riscv/static/fonts/glyphicons-halflings-regular.woff2
puncover_riscv/static/icons/Document_16x.svg
puncover_riscv/static/icons/Field_16x.svg
puncover_riscv/static/icons/FolderOpen_16x.svg
puncover_riscv/static/icons/Folder_16x.svg
puncover_riscv/static/icons/Method_16x.svg
puncover_riscv/static/icons/readme.md
puncover_riscv/static/js/bootstrap.min.js
puncover_riscv/templates/all_symbols.html.jinja
puncover_riscv/templates/base.html.jinja
puncover_riscv/templates/file.html.jinja
puncover_riscv/templates/folder.html.jinja
puncover_riscv/templates/lists.html.jinja
puncover_riscv/templates/overview.html.jinja
puncover_riscv/templates/rack.html.jinja
puncover_riscv/templates/symbol.html.jinja
puncover_riscv-0.2.3.dist-info/LICENSE.txt
puncover_riscv-0.2.3.dist-info/METADATA
puncover_riscv-0.2.3.dist-info/WHEEL
puncover_riscv-0.2.3.dist-info/entry_points.txt
puncover_riscv-0.2.3.dist-info/top_level.txt
puncover_riscv-0.2.3.dist-info/RECORD
