Metadata-Version: 2.1
Name: puncover-riscv
Version: 0.2.3
Summary: Analyses RISCV C/C++ build output for code size, static variables, and stack usage.
Home-page: https://github.com/Egahp/puncover_riscv
Author: Egahp
License: MIT
Download-URL: https://github.com/Egahp/puncover_riscv/tarball/0.2.3
Platform: UNKNOWN
Classifier: Development Status :: 5 - Production/Stable
Classifier: Intended Audience :: Developers
Classifier: Natural Language :: English
Classifier: License :: OSI Approved :: MIT License
Classifier: Programming Language :: Python
Classifier: Programming Language :: Python :: 3
Classifier: Programming Language :: Python :: 3.6
Classifier: Programming Language :: Python :: 3.7
Classifier: Programming Language :: Python :: 3.8
Classifier: Programming Language :: Python :: 3.9
Classifier: Programming Language :: Python :: 3.10
Classifier: Programming Language :: Python :: 3.11
Requires-Python: >=3.6
Requires-Dist: Flask (==2.0.3)
Requires-Dist: jinja2 (==3.0.0)
Requires-Dist: werkzeug (==2.0.2)
